{
    "paper_layouts": {
        "letter": {
            "width": 3300,
            "height": 2550,
            "card_layouts": {
                "standard": {
                    "width": 742,
                    "height": 1034,
                    "x_pos": [
                        141,
                        900,
                        1658,
                        2417
                    ],
                    "y_pos": [
                        234,
                        1283
                    ],
                    "template": "letter_standard_v2"
                },
                "bridge": {
                    "width": 673,
                    "height": 1048,
                    "x_pos": [
                        256,
                        961,
                        1666,
                        2371
                    ],
                    "y_pos": [
                        214,
                        1288
                    ],
                    "template": "letter_bridge_v2"
                },
                "poker": {
                    "width": 748,
                    "height": 1048,
                    "x_pos": [
                        132,
                        895,
                        1657,
                        2420
                    ],
                    "y_pos": [
                        220,
                        1283
                    ],
                    "template": "letter_poker_v2"
                },
                "poker_half": {
                    "width": 523,
                    "height": 733,
                    "x_pos": [
                        265,
                        827,
                        1388,
                        1950,
                        2512
                    ],
                    "y_pos": [
                        142,
                        908,
                        1674
                    ],
                    "template": "letter_pokerhalf_v2"
                }
            }
        },
        "a4": {
            "width": 3509,
            "height": 2481,
            "card_layouts": {
                "standard": {
                    "width": 742,
                    "height": 1034,
                    "x_pos": [
                        245,
                        1004,
                        1764,
                        2521
                    ],
                    "y_pos": [
                        199,
                        1248
                    ],
                    "template": "a4_standard_v1"
                },
                "bridge": {
                    "width": 673,
                    "height": 1048,
                    "x_pos": [
                        344,
                        1049,
                        1754,
                        2459
                    ],
                    "y_pos": [
                        165,
                        1239
                    ],
                    "template": "a4_bridge_v1"
                },
                "poker": {
                    "width": 748,
                    "height": 1048,
                    "x_pos": [
                        236,
                        999,
                        1761,
                        2524
                    ],
                    "y_pos": [
                        185,
                        1248
                    ],
                    "template": "a4_poker_v1"
                },
                "poker_half": {
                    "width": 523,
                    "height": 733,
                    "x_pos": [
                        369,
                        931,
                        1492,
                        2054,
                        2616
                    ],
                    "y_pos": [
                        120,
                        886,
                        1652
                    ],
                    "template": "a4_pokerhalf_v1"
                }
            }
        }
    }
}